<?xml version="1.0" encoding="UTF-8"?>
<!DOCTYPE mapper PUBLIC "-//mybatis.org//DTD Mapper 3.0//EN" "http://mybatis.org/dtd/mybatis-3-mapper.dtd">
<mapper namespace="com.xiexin.dao.ComputerDAO">
  <resultMap id="BaseResultMap" type="com.xiexin.bean.Computer">
    <id column="pc_id" jdbcType="INTEGER" property="pcId" />
    <result column="pc_name" jdbcType="VARCHAR" property="pcName" />
    <result column="pc_memory" jdbcType="VARCHAR" property="pcMemory" />
    <result column="pc_cpu" jdbcType="VARCHAR" property="pcCpu" />
    <result column="pc_videocard" jdbcType="VARCHAR" property="pcVideocard" />
    <result column="pc_display" jdbcType="VARCHAR" property="pcDisplay" />
    <result column="pc_hdd" jdbcType="VARCHAR" property="pcHdd" />
    <result column="pc_price" jdbcType="VARCHAR" property="pcPrice" />
  </resultMap>
  <sql id="Example_Where_Clause">
    <where>
      <foreach collection="oredCriteria" item="criteria" separator="or">
        <if test="criteria.valid">
          <trim prefix="(" prefixOverrides="and" suffix=")">
            <foreach collection="criteria.criteria" item="criterion">
              <choose>
                <when test="criterion.noValue">
                  and ${criterion.condition}
                </when>
                <when test="criterion.singleValue">
                  and ${criterion.condition} #{criterion.value}
                </when>
                <when test="criterion.betweenValue">
                  and ${criterion.condition} #{criterion.value} and #{criterion.secondValue}
                </when>
                <when test="criterion.listValue">
                  and ${criterion.condition}
                  <foreach close=")" collection="criterion.value" item="listItem" open="(" separator=",">
                    #{listItem}
                  </foreach>
                </when>
              </choose>
            </foreach>
          </trim>
        </if>
      </foreach>
    </where>
  </sql>
  <sql id="Update_By_Example_Where_Clause">
    <where>
      <foreach collection="example.oredCriteria" item="criteria" separator="or">
        <if test="criteria.valid">
          <trim prefix="(" prefixOverrides="and" suffix=")">
            <foreach collection="criteria.criteria" item="criterion">
              <choose>
                <when test="criterion.noValue">
                  and ${criterion.condition}
                </when>
                <when test="criterion.singleValue">
                  and ${criterion.condition} #{criterion.value}
                </when>
                <when test="criterion.betweenValue">
                  and ${criterion.condition} #{criterion.value} and #{criterion.secondValue}
                </when>
                <when test="criterion.listValue">
                  and ${criterion.condition}
                  <foreach close=")" collection="criterion.value" item="listItem" open="(" separator=",">
                    #{listItem}
                  </foreach>
                </when>
              </choose>
            </foreach>
          </trim>
        </if>
      </foreach>
    </where>
  </sql>
  <sql id="Base_Column_List">
    pc_id, pc_name, pc_memory, pc_cpu, pc_videocard, pc_display, pc_hdd, pc_price
  </sql>
  <select id="selectByExample" parameterType="com.xiexin.bean.ComputerExample" resultMap="BaseResultMap">
    select
    <if test="distinct">
      distinct
    </if>
    <include refid="Base_Column_List" />
    from computer
    <if test="_parameter != null">
      <include refid="Example_Where_Clause" />
    </if>
    <if test="orderByClause != null">
      order by ${orderByClause}
    </if>
    <if test="limit != null">
      <if test="offset != null">
        limit ${offset}, ${limit}
      </if>
      <if test="offset == null">
        limit ${limit}
      </if>
    </if>
  </select>
  <select id="selectByPrimaryKey" parameterType="java.lang.Integer" resultMap="BaseResultMap">
    select 
    <include refid="Base_Column_List" />
    from computer
    where pc_id = #{pcId,jdbcType=INTEGER}
  </select>
  <delete id="deleteByPrimaryKey" parameterType="java.lang.Integer">
    delete from computer
    where pc_id = #{pcId,jdbcType=INTEGER}
  </delete>
  <delete id="deleteByExample" parameterType="com.xiexin.bean.ComputerExample">
    delete from computer
    <if test="_parameter != null">
      <include refid="Example_Where_Clause" />
    </if>
  </delete>
  <insert id="insert" parameterType="com.xiexin.bean.Computer">
    insert into computer (pc_id, pc_name, pc_memory, 
      pc_cpu, pc_videocard, pc_display, 
      pc_hdd, pc_price)
    values (#{pcId,jdbcType=INTEGER}, #{pcName,jdbcType=VARCHAR}, #{pcMemory,jdbcType=VARCHAR}, 
      #{pcCpu,jdbcType=VARCHAR}, #{pcVideocard,jdbcType=VARCHAR}, #{pcDisplay,jdbcType=VARCHAR}, 
      #{pcHdd,jdbcType=VARCHAR}, #{pcPrice,jdbcType=VARCHAR})
  </insert>
  <insert id="insertSelective" parameterType="com.xiexin.bean.Computer">
    insert into computer
    <trim prefix="(" suffix=")" suffixOverrides=",">
      <if test="pcId != null">
        pc_id,
      </if>
      <if test="pcName != null">
        pc_name,
      </if>
      <if test="pcMemory != null">
        pc_memory,
      </if>
      <if test="pcCpu != null">
        pc_cpu,
      </if>
      <if test="pcVideocard != null">
        pc_videocard,
      </if>
      <if test="pcDisplay != null">
        pc_display,
      </if>
      <if test="pcHdd != null">
        pc_hdd,
      </if>
      <if test="pcPrice != null">
        pc_price,
      </if>
    </trim>
    <trim prefix="values (" suffix=")" suffixOverrides=",">
      <if test="pcId != null">
        #{pcId,jdbcType=INTEGER},
      </if>
      <if test="pcName != null">
        #{pcName,jdbcType=VARCHAR},
      </if>
      <if test="pcMemory != null">
        #{pcMemory,jdbcType=VARCHAR},
      </if>
      <if test="pcCpu != null">
        #{pcCpu,jdbcType=VARCHAR},
      </if>
      <if test="pcVideocard != null">
        #{pcVideocard,jdbcType=VARCHAR},
      </if>
      <if test="pcDisplay != null">
        #{pcDisplay,jdbcType=VARCHAR},
      </if>
      <if test="pcHdd != null">
        #{pcHdd,jdbcType=VARCHAR},
      </if>
      <if test="pcPrice != null">
        #{pcPrice,jdbcType=VARCHAR},
      </if>
    </trim>
  </insert>
  <select id="countByExample" parameterType="com.xiexin.bean.ComputerExample" resultType="java.lang.Long">
    select count(*) from computer
    <if test="_parameter != null">
      <include refid="Example_Where_Clause" />
    </if>
  </select>
  <update id="updateByExampleSelective" parameterType="map">
    update computer
    <set>
      <if test="record.pcId != null">
        pc_id = #{record.pcId,jdbcType=INTEGER},
      </if>
      <if test="record.pcName != null">
        pc_name = #{record.pcName,jdbcType=VARCHAR},
      </if>
      <if test="record.pcMemory != null">
        pc_memory = #{record.pcMemory,jdbcType=VARCHAR},
      </if>
      <if test="record.pcCpu != null">
        pc_cpu = #{record.pcCpu,jdbcType=VARCHAR},
      </if>
      <if test="record.pcVideocard != null">
        pc_videocard = #{record.pcVideocard,jdbcType=VARCHAR},
      </if>
      <if test="record.pcDisplay != null">
        pc_display = #{record.pcDisplay,jdbcType=VARCHAR},
      </if>
      <if test="record.pcHdd != null">
        pc_hdd = #{record.pcHdd,jdbcType=VARCHAR},
      </if>
      <if test="record.pcPrice != null">
        pc_price = #{record.pcPrice,jdbcType=VARCHAR},
      </if>
    </set>
    <if test="_parameter != null">
      <include refid="Update_By_Example_Where_Clause" />
    </if>
  </update>
  <update id="updateByExample" parameterType="map">
    update computer
    set pc_id = #{record.pcId,jdbcType=INTEGER},
      pc_name = #{record.pcName,jdbcType=VARCHAR},
      pc_memory = #{record.pcMemory,jdbcType=VARCHAR},
      pc_cpu = #{record.pcCpu,jdbcType=VARCHAR},
      pc_videocard = #{record.pcVideocard,jdbcType=VARCHAR},
      pc_display = #{record.pcDisplay,jdbcType=VARCHAR},
      pc_hdd = #{record.pcHdd,jdbcType=VARCHAR},
      pc_price = #{record.pcPrice,jdbcType=VARCHAR}
    <if test="_parameter != null">
      <include refid="Update_By_Example_Where_Clause" />
    </if>
  </update>
  <update id="updateByPrimaryKeySelective" parameterType="com.xiexin.bean.Computer">
    update computer
    <set>
      <if test="pcName != null">
        pc_name = #{pcName,jdbcType=VARCHAR},
      </if>
      <if test="pcMemory != null">
        pc_memory = #{pcMemory,jdbcType=VARCHAR},
      </if>
      <if test="pcCpu != null">
        pc_cpu = #{pcCpu,jdbcType=VARCHAR},
      </if>
      <if test="pcVideocard != null">
        pc_videocard = #{pcVideocard,jdbcType=VARCHAR},
      </if>
      <if test="pcDisplay != null">
        pc_display = #{pcDisplay,jdbcType=VARCHAR},
      </if>
      <if test="pcHdd != null">
        pc_hdd = #{pcHdd,jdbcType=VARCHAR},
      </if>
      <if test="pcPrice != null">
        pc_price = #{pcPrice,jdbcType=VARCHAR},
      </if>
    </set>
    where pc_id = #{pcId,jdbcType=INTEGER}
  </update>
  <update id="updateByPrimaryKey" parameterType="com.xiexin.bean.Computer">
    update computer
    set pc_name = #{pcName,jdbcType=VARCHAR},
      pc_memory = #{pcMemory,jdbcType=VARCHAR},
      pc_cpu = #{pcCpu,jdbcType=VARCHAR},
      pc_videocard = #{pcVideocard,jdbcType=VARCHAR},
      pc_display = #{pcDisplay,jdbcType=VARCHAR},
      pc_hdd = #{pcHdd,jdbcType=VARCHAR},
      pc_price = #{pcPrice,jdbcType=VARCHAR}
    where pc_id = #{pcId,jdbcType=INTEGER}
  </update>
</mapper>